osrs_highscores/__init__.py
osrs_highscores/__version__.py
osrs_highscores/base.py
osrs_highscores/highscores.py
osrs_highscores/rankings.py
osrs_highscores/resources/__init__.py
osrs_highscores/resources/categories.py
osrs_highscores/resources/utils.py
tests/__init__.py
tests/test_highscores.py
tests/test_rankings.py
osrs_highscores-0.9.0.dist-info/LICENSE
osrs_highscores-0.9.0.dist-info/METADATA
osrs_highscores-0.9.0.dist-info/WHEEL
osrs_highscores-0.9.0.dist-info/top_level.txt
osrs_highscores-0.9.0.dist-info/RECORD
