Metadata-Version: 2.1
Name: osrs_highscores
Version: 0.9.0
Summary: Simple Wrapper for the OSRS Highscores
Home-page: https://github.com/matthew-palmer/osrs_highscores
Author: Matthew Palmer
Author-email: palmer.matthew167@gmail.com
License: MIT License
Classifier: Programming Language :: Python :: 3
Classifier: License :: OSI Approved :: MIT License
Classifier: Operating System :: OS Independent
Requires-Python: >=3.7
License-File: LICENSE
Requires-Dist: requests ==2.27.1
Requires-Dist: beautifulsoup4 ==4.11.1
Requires-Dist: addict ==2.4.0
